voyager_prime/__init__.py
voyager_prime/main.py
voyager_prime-0.1.0.dist-info/METADATA
voyager_prime-0.1.0.dist-info/WHEEL
voyager_prime-0.1.0.dist-info/top_level.txt
voyager_prime-0.1.0.dist-info/RECORD
