Metadata-Version: 2.1
Name: voyager_prime
Version: 0.1.0
Summary: A simple but useful library for work with prime numbers
Home-page: https://github.com/yourusername/voyager_prime
Author: Olaf Baca
Author-email: olaf.baca@hotmail.com
Classifier: Programming Language :: Python :: 3
Classifier: License :: OSI Approved :: MIT License
Classifier: Operating System :: OS Independent
Requires-Python: >=3.6
